ccore/__init__.py
ccore/_ccore.cpython-38-x86_64-linux-gnu.so
ccore-0.2.8.dist-info/LICENSE
ccore-0.2.8.dist-info/METADATA
ccore-0.2.8.dist-info/WHEEL
ccore-0.2.8.dist-info/top_level.txt
ccore-0.2.8.dist-info/RECORD
