Metadata-Version: 2.1
Name: ccore
Version: 0.2.8
Summary: ccore description
Home-page: https://github.com/kirin123kirin/ccore
Author: kirin123kirin
License: MIT
Keywords: encoding,list,iterator,open,core,util,utility
Platform: any
Classifier: Programming Language :: Python :: 2.7
Classifier: Programming Language :: Python :: 3
Classifier: Programming Language :: Python :: 3.6
Classifier: Programming Language :: Python :: 3.7
Classifier: Programming Language :: Python :: 3.8
Classifier: Programming Language :: Python :: 3.9
Classifier: License :: OSI Approved :: MIT License
Classifier: Environment :: Console
Classifier: Operating System :: POSIX :: Linux
Classifier: Operating System :: Unix
Classifier: Operating System :: MacOS
Classifier: Operating System :: Microsoft :: Windows
License-File: LICENSE
Requires-Dist: setuptools (>=42)
Requires-Dist: wheel
Requires-Dist: scikit-build (>=0.12)
Requires-Dist: cmake (>=3.18)
Provides-Extra: test
Requires-Dist: pytest ; extra == 'test'
Requires-Dist: pytest-cov ; extra == 'test'
Requires-Dist: psutil ; extra == 'test'
